mathgenerator/__init__.py
mathgenerator/generator.py
mathgenerator/latexBuilder.py
mathgenerator/mathgen.py
mathgenerator/funcs/__init__.py
mathgenerator/funcs/template.py
mathgenerator/funcs/template_comments.py
mathgenerator/funcs/algebra/__init__.py
mathgenerator/funcs/algebra/basic_algebra.py
mathgenerator/funcs/algebra/combine_like_terms.py
mathgenerator/funcs/algebra/complex_quadratic.py
mathgenerator/funcs/algebra/compound_interest.py
mathgenerator/funcs/algebra/distance_two_points.py
mathgenerator/funcs/algebra/expanding.py
mathgenerator/funcs/algebra/factoring.py
mathgenerator/funcs/algebra/int_matrix_22_determinant.py
mathgenerator/funcs/algebra/intersection_of_two_lines.py
mathgenerator/funcs/algebra/invert_matrix.py
mathgenerator/funcs/algebra/linear_equations.py
mathgenerator/funcs/algebra/log.py
mathgenerator/funcs/algebra/matrix_multiplication.py
mathgenerator/funcs/algebra/midpoint_of_two_points.py
mathgenerator/funcs/algebra/multiply_complex_numbers.py
mathgenerator/funcs/algebra/multiply_int_to_22_matrix.py
mathgenerator/funcs/algebra/quadratic_equation.py
mathgenerator/funcs/algebra/simple_interest.py
mathgenerator/funcs/algebra/system_of_equations.py
mathgenerator/funcs/algebra/vector_cross.py
mathgenerator/funcs/algebra/vector_dot.py
mathgenerator/funcs/basic_math/__init__.py
mathgenerator/funcs/basic_math/absolute_difference.py
mathgenerator/funcs/basic_math/addition.py
mathgenerator/funcs/basic_math/compare_fractions.py
mathgenerator/funcs/basic_math/cube_root.py
mathgenerator/funcs/basic_math/divide_fractions.py
mathgenerator/funcs/basic_math/division.py
mathgenerator/funcs/basic_math/exponentiation.py
mathgenerator/funcs/basic_math/factorial.py
mathgenerator/funcs/basic_math/fraction_multiplication.py
mathgenerator/funcs/basic_math/fraction_to_decimal.py
mathgenerator/funcs/basic_math/greatest_common_divisor.py
mathgenerator/funcs/basic_math/is_composite.py
mathgenerator/funcs/basic_math/is_prime.py
mathgenerator-1.5.0.dist-info/LICENSE
mathgenerator-1.5.0.dist-info/METADATA
mathgenerator-1.5.0.dist-info/WHEEL
mathgenerator-1.5.0.dist-info/top_level.txt
mathgenerator-1.5.0.dist-info/RECORD
